inspect_recursive/__init__.py
inspect_recursive/inspect_object_structure.py
inspect_recursive-0.1.0.dist-info/LICENSE
inspect_recursive-0.1.0.dist-info/METADATA
inspect_recursive-0.1.0.dist-info/WHEEL
inspect_recursive-0.1.0.dist-info/RECORD
