Metadata-Version: 2.1
Name: inspect-recursive
Version: 0.1.0
Summary: 
Author: hermann-web
Author-email: hermannagossou6@gmail.com
Requires-Python: >=3.8.1,<4.0.0
Classifier: Programming Language :: Python :: 3
Classifier: Programming Language :: Python :: 3.9
Classifier: Programming Language :: Python :: 3.10
Classifier: Programming Language :: Python :: 3.11
Classifier: Programming Language :: Python :: 3.12
